PythonTsa/CheckStationarynInvertible.py
PythonTsa/CointegrationTest.py
PythonTsa/LjungBoxtest.py
PythonTsa/ModResidDiag.py
PythonTsa/MultiCorrPvalue.py
PythonTsa/RandomWalk.py
PythonTsa/SeasonalRW.py
PythonTsa/Selecting_arma.py
PythonTsa/Selecting_arma2.py
PythonTsa/SimulSBM.py
PythonTsa/True_acf.py
PythonTsa/TsTensor.py
PythonTsa/__init__.py
PythonTsa/datadir.py
PythonTsa/openPDF.py
PythonTsa/plot_acf_pacf.py
PythonTsa/plot_multi_ACF.py
PythonTsa/plot_multi_Q_pvalue.py
PythonTsa/Ptsadata/AntidiabeticDrugSales.csv
PythonTsa/Ptsadata/AustraliaEmployedTotalPersons.xlsx
PythonTsa/Ptsadata/AustraliaUnemployedTotalPersons.xlsx
PythonTsa/Ptsadata/BitcoinPrice17-6-23-18-6-22.xlsx
PythonTsa/Ptsadata/DAX.csv
PythonTsa/Ptsadata/DAXlogret.csv
PythonTsa/Ptsadata/EconGermany.dat
PythonTsa/Ptsadata/ExchRate NZ per UK.txt
PythonTsa/Ptsadata/Global mean surface air temp changes 1880-1985.csv
PythonTsa/Ptsadata/GlobalTemperature.txt
PythonTsa/Ptsadata/IBM.csv
PythonTsa/Ptsadata/Noboyngirl.csv
PythonTsa/Ptsadata/RwalkwDrift0.3.csv
PythonTsa/Ptsadata/SP500dailyreturns.csv
PythonTsa/Ptsadata/Southtemperature.txt
PythonTsa/Ptsadata/USEconomicChange.csv
PythonTsa/Ptsadata/USFemalesAged20+Job1948-81.csv
PythonTsa/Ptsadata/USQgdpunemp.csv
PythonTsa/Ptsadata/USbill.csv
PythonTsa/Ptsadata/USmacronInRate.txt
PythonTsa/Ptsadata/WTI-Brent.csv
PythonTsa/Ptsadata/Yearly mean total sunspot number 1700 - 2017.csv
PythonTsa/Ptsadata/areturns.csv
PythonTsa/Ptsadata/chaos.csv
PythonTsa/Ptsadata/dlGDPukcaus1q1980.csv
PythonTsa/Ptsadata/elec-temp.csv
PythonTsa/Ptsadata/gdpquarterlychina1992.1-2017.4.csv
PythonTsa/Ptsadata/h02July1991June2008.csv
PythonTsa/Ptsadata/ibmlogret.csv
PythonTsa/Ptsadata/milk.xlsx
PythonTsa/Ptsadata/monthly returns of PG stock 1961 to 2016.csv
PythonTsa/Ptsadata/monthly returns of Procter n Gamble stock n 3 market indexes 1961 to 2016.csv
PythonTsa/Ptsadata/nao.csv
PythonTsa/Ptsadata/realGdpConsInv.csv
PythonTsa/Ptsadata/us-q-rgdp.csv
PythonTsa/Ptsadata/usFOI.csv
pythontsa-1.5.3.dist-info/METADATA
pythontsa-1.5.3.dist-info/WHEEL
pythontsa-1.5.3.dist-info/top_level.txt
pythontsa-1.5.3.dist-info/RECORD
