Metadata-Version: 2.4
Name: PythonTsa
Version: 1.5.3
Summary: Package for Applied Time Series Analysis and Forecasting with Python, Springer 2022
Home-page: https://github.com/QuantLet/pyTSA
Author: Changquan Huang
Author-email: h.changquan@icloud.com
Classifier: Programming Language :: Python :: 3
Classifier: License :: OSI Approved :: MIT License
Classifier: Operating System :: OS Independent
Requires-Python: >=3.6
Dynamic: author
Dynamic: author-email
Dynamic: classifier
Dynamic: description
Dynamic: description-content-type
Dynamic: home-page
Dynamic: requires-python
Dynamic: summary
